payment_page_sdk/__init__.py
payment_page_sdk/callback.py
payment_page_sdk/gate.py
payment_page_sdk/payment.py
payment_page_sdk/payment_page.py
payment_page_sdk/process_exception.py
payment_page_sdk/signature_handler.py
itechpsp_sdk-1.0.3.dist-info/LICENSE
itechpsp_sdk-1.0.3.dist-info/METADATA
itechpsp_sdk-1.0.3.dist-info/WHEEL
itechpsp_sdk-1.0.3.dist-info/top_level.txt
itechpsp_sdk-1.0.3.dist-info/RECORD
